moldf/__init__.py
moldf/constants.py
moldf/covalent_bond.py
moldf/pdb_dataframe.py
moldf/read_jcsv.py
moldf/read_mol2.py
moldf/read_pdb.py
moldf/read_pdbx.py
moldf/split_line.py
moldf/version.py
moldf/write_jcsv.py
moldf/write_mol2.py
moldf/write_pdb.py
moldf/write_pdbx.py
moldf/covalent_bonds/ALA.cif
moldf/covalent_bonds/ARG.cif
moldf/covalent_bonds/ASN.cif
moldf/covalent_bonds/ASP.cif
moldf/covalent_bonds/CYS.cif
moldf/covalent_bonds/GLN.cif
moldf/covalent_bonds/GLU.cif
moldf/covalent_bonds/GLY.cif
moldf/covalent_bonds/HIS.cif
moldf/covalent_bonds/ILE.cif
moldf/covalent_bonds/LEU.cif
moldf/covalent_bonds/LYS.cif
moldf/covalent_bonds/MET.cif
moldf/covalent_bonds/PHE.cif
moldf/covalent_bonds/PRO.cif
moldf/covalent_bonds/PYL.cif
moldf/covalent_bonds/SEC.cif
moldf/covalent_bonds/SER.cif
moldf/covalent_bonds/THR.cif
moldf/covalent_bonds/TRP.cif
moldf/covalent_bonds/TYR.cif
moldf/covalent_bonds/VAL.cif
moldf/covalent_bonds/__init__.py
moldf/covalent_bonds/covalent_radii.csv
tests/__init__.py
tests/conftest.py
tests/test_covalent_bond.py
tests/test_pdb_dataframe.py
tests/test_read_jcsv.py
tests/test_read_mol2.py
tests/test_read_pdb.py
tests/test_read_pdbx.py
tests/test_split_line.py
tests/test_write_jcsv.py
tests/test_write_mol2.py
tests/test_write_pdb.py
tests/test_write_pdbx.py
moldf-0.7.5.dist-info/LICENSE
moldf-0.7.5.dist-info/METADATA
moldf-0.7.5.dist-info/WHEEL
moldf-0.7.5.dist-info/top_level.txt
moldf-0.7.5.dist-info/RECORD
