Metadata-Version: 2.1
Name: moldf
Version: 0.7.5
Summary: Super lightweight and fast mmCIF/PDB/MOL2 file parser into Pandas DataFrames and backwards writer.
Home-page: https://github.com/Ruibin-Liu/MolDF
Author: Ruibin Liu
Author-email: ruibinliuphd@gmail.com
Project-URL: Bug Tracker, https://github.com/Ruibin-Liu/MolDF/issues
Project-URL: Documentation, https://moldf.readthedocs.io/en/stable/
Classifier: Programming Language :: Python :: 3
Classifier: License :: OSI Approved :: MIT License
Classifier: Operating System :: OS Independent
Requires-Python: >=3.7
License-File: LICENSE
Requires-Dist: scipy >=1.0
Requires-Dist: pandas >=1.0
Provides-Extra: testing
Requires-Dist: tox >=3.24 ; extra == 'testing'
Requires-Dist: pytest >=7.0 ; extra == 'testing'
Requires-Dist: pytest-cov >=3.0 ; extra == 'testing'
